{
  "9818462066": {
    "name": "Rohit",
    "phone": "9818462066",
    "email": "",
    "total_purchases": 423.0,
    "last_visit": "2025-08-15",
    "loyalty_points": 1
  },
  "9911108114": {
    "name": "karan",
    "phone": "9911108114",
    "email": "",
    "total_purchases": 58.0,
    "last_visit": "2025-08-15",
    "loyalty_points": 2
  },
  "rahul": {
    "name": "rahul",
    "phone": "rahul",
    "email": "",
    "total_purchases": 1.0,
    "last_visit": "2025-08-15",
    "loyalty_points": 1
  },
  "9599402644": {
    "name": "SHYAM",
    "phone": "9599402644",
    "email": "",
    "total_purchases": 177.0,
    "last_visit": "2025-08-15",
    "loyalty_points": 1
  },
  "8287258412": {
    "name": "OM",
    "phone": "8287258412",
    "email": "",
    "total_purchases": 88.0,
    "last_visit": "2025-08-16",
    "loyalty_points": 1
  },
  "OM": {
    "name": "OM",
    "phone": "OM",
    "email": "",
    "total_purchases": 95.0,
    "last_visit": "2025-08-16",
    "loyalty_points": 1
  },
  "WALKIN": {
    "name": "WALKIN",
    "phone": "WALKIN",
    "email": "",
    "total_purchases": 480.0,
    "last_visit": "2025-08-16",
    "loyalty_points": 4
  },
  "8447703762": {
    "name": "MANOJ",
    "phone": "8447703762",
    "email": "",
    "total_purchases": 280.0,
    "last_visit": "2025-08-16",
    "loyalty_points": 1
  },
  "989595965656": {
    "name": "MALINGA",
    "phone": "989595965656",
    "email": "",
    "total_purchases": 117.0,
    "last_visit": "2025-08-16",
    "loyalty_points": 1
  },
  "8377058667": {
    "name": "SHREYASH",
    "phone": "8377058667",
    "email": "",
    "total_purchases": 1100.0,
    "last_visit": "2025-08-16",
    "loyalty_points": 1
  },
  "test": {
    "name": "test",
    "phone": "test",
    "email": "",
    "total_purchases": 317.0,
    "last_visit": "2025-08-17",
    "loyalty_points": 2
  },
  "test2": {
    "name": "test2",
    "phone": "test2",
    "email": "",
    "total_purchases": 278.0,
    "last_visit": "2025-08-17",
    "loyalty_points": 1
  }
}